[
{
	"section": "3D",
	"children":
	[
		{
			"name": "Allemagne",
			"value": 2
		},
		{
			"name": "Angola",
			"value": 1
		},
		{
			"name": "Belgique",
			"value": 436
		},
		{
			"name": "Bulgarie",
			"value": 4
		},
		{
			"name": "Cameroun",
			"value": 2
		},
		{
			"name": "Chine",
			"value": 2
		},
		{
			"name": "Congo",
			"value": 1
		},
		{
			"name": "Côte d'Ivoire",
			"value": 3
		},
		{
			"name": "Espagne",
			"value": 3
		},
		{
			"name": "France",
			"value": 151
		},
		{
			"name": "Grande-Bretagne",
			"value": 4
		},
		{
			"name": "Italie",
			"value": 1
		},
		{
			"name": "Luxembourg",
			"value": 5
		},
		{
			"name": "Maroc",
			"value": 2
		},
		{
			"name": "Pologne",
			"value": 1
		},
		{
			"name": "Portugal",
			"value": 1
		},
		{
			"name": "Roumanie",
			"value": 1
		},
		{
			"name": "Russie",
			"value": 2
		},
		{
			"name": "Tunisie",
			"value": 2
		}
	]
},

{
	"section": "JV",
	"children":
	[
		{
			"name": "Allemagne",
			"value": 2
		},
		{
			"name": "Belgique",
			"value": 370
		},
		{
			"name": "Espagne",
			"value": 1
		},
		{
			"name": "France",
			"value": 150
		},
		{
			"name": "Moldavie",
			"value": 2
		},
		{
			"name": "Pays-Bas",
			"value": 2
		},
		{
			"name": "Pérou",
			"value": 1
		},
		{
			"name": "Pologne",
			"value": 3
		},
		{
			"name": "Portugal",
			"value": 1
		}
	]
},

{
	"section": "PP",
	"children":
	[
		{
			"name": "Belgique",
			"value": 411
		},
		{
			"name": "Cameroun",
			"value": 3
		},
		{
			"name": "France",
			"value": 43
		},
		{
			"name": "Grande-Bretagne",
			"value": 1
		},
		{
			"name": "Luxembourg",
			"value": 3
		},
		{
			"name": "Roumanie",
			"value": 4
		},
		{
			"name": "Russie",
			"value": 1
		}
	]
},

{
	"section": "DWM",
	"children":
	[
		{
			"name": "Algérie",
			"value": 1
		},
		{
			"name": "Belgique",
			"value": 369
		},
		{
			"name": "Cameroun",
			"value": 3
		},
		{
			"name": "Equateur",
			"value": 1
		},
		{
			"name": "Espagne",
			"value": 1
		},
		{
			"name": "France",
			"value": 69
		},
		{
			"name": "Grande-Bretagne",
			"value": 1
		},
		{
			"name": "Italie",
			"value": 4
		},
		{
			"name": "Jordanie",
			"value": 1
		},
		{
			"name": "Luxembourg",
			"value": 2
		},
		{
			"name": "Pologne",
			"value": 5
		},
		{
			"name": "Portugal",
			"value": 3
		},
		{
			"name": "Roumanie",
			"value": 1
		}
	]
},

{
	"section": "ANIM",
	"children":
	[
		{
			"name": "Allemagne",
			"value": 1
		},
		{
			"name": "Belgique",
			"value": 229
		},
		{
			"name": "Cameroun",
			"value": 1
		},
		{
			"name": "Espagne",
			"value": 2
		},
		{
			"name": "France",
			"value": 93
		},
		{
			"name": "Luxembourg",
			"value": 1
		},
		{
			"name": "Tunisie",
			"value": 1
		}
	]
},

{
	"section": "TOUS",
	"children":
	[
		{
			"name": "Algérie",
			"value": 1
		},
		{
			"name": "Allemagne",
			"value": 5
		},
		{
			"name": "Angola",
			"value": 1
		},
		{
			"name": "Belgique",
			"value": 1815
		},
		{
			"name": "Bulgarie",
			"value": 4
		},
		{
			"name": "Cameroun",
			"value": 9
		},
		{
			"name": "Chine",
			"value": 2
		},
		{
			"name": "Congo",
			"value": 1
		},
		{
			"name": "Côte d'Ivoire",
			"value": 3
		},
		{
			"name": "Equateur",
			"value": 1
		},
		{
			"name": "Espagne",
			"value": 7
		},
		{
			"name": "France",
			"value": 506
		},
		{
			"name": "Grande-Bretagne",
			"value": 6
		},
		{
			"name": "Italie",
			"value": 5
		},
		{
			"name": "Jordanie",
			"value": 1
		},
		{
			"name": "Luxembourg",
			"value": 11
		},
		{
			"name": "Maroc",
			"value": 2
		},
		{
			"name": "Moldavie",
			"value": 2
		},
		{
			"name": "Pays-Bas",
			"value": 2
		},
		{
			"name": "Pérou",
			"value": 1
		},
		{
			"name": "Pologne",
			"value": 9
		},
		{
			"name": "Portugal",
			"value": 5
		},
		{
			"name": "Roumanie",
			"value": 6
		},
		{
			"name": "Russie",
			"value": 3
		},
		{
			"name": "Tunisie",
			"value": 3
		}
	]
}
]